[
  {
    "id": "p1",
    "name": "Pilot V7",
    "price": 70,
    "image": "/da.png",
    "description": "Comfortable over-ear wireless headphones with noise cancellation."
  },
  {
    "id": "p2",
    "name": "Pilot Juice Up",
    "price": 370,
    "image": "da2.png",
    "description": "Health tracking, notifications and long battery life."
  },
  {
    "id": "p3",
    "name": "Camlin Whiteout",
    "price": 40,
    "image": "da3.png",
    "description": "Rugged, waterproof bluetooth speaker with punchy bass."
  }
]